convert_stream/__init__.py
convert_stream/__main__.py
convert_stream/_version.py
convert_stream/doc_stream.py
convert_stream/table_files.py
convert_stream/convert/__init__.py
convert_stream/convert/image_to_pdf.py
convert_stream/convert/pdf_to_image.py
convert_stream/image/__init__.py
convert_stream/image/img_object.py
convert_stream/mod_types/__init__.py
convert_stream/mod_types/enums.py
convert_stream/mod_types/modules.py
convert_stream/pdf/__init__.py
convert_stream/pdf/pdf_document.py
convert_stream/pdf/pdf_page.py
convert_stream/text/__init__.py
convert_stream/text/find_text.py
convert_stream/text/terminal.py
convert_stream-2.5.1.dist-info/METADATA
convert_stream-2.5.1.dist-info/WHEEL
convert_stream-2.5.1.dist-info/top_level.txt
convert_stream-2.5.1.dist-info/RECORD
