Metadata-Version: 2.4
Name: convert_stream
Version: 2.5.1
Summary: Manipulação de documentos PDF e Imagens. Converter, Ler, rotacionar exportar etc.
Author: Bruno Chaves
Requires-Python: >=3.11
Requires-Dist: soup_files>=1.4.2
Requires-Dist: PyMuPDF
Requires-Dist: scipy
Requires-Dist: reportlab
Requires-Dist: openpyxl
Requires-Dist: odfpy
Requires-Dist: pandas
Requires-Dist: Pillow>=11.3.0
Requires-Dist: opencv-python
Requires-Dist: requests>=2.32.4
Requires-Dist: sheet_stream>=0.1.3
